haoline/__init__.py
haoline/__main__.py
haoline/_cli_legacy.py
haoline/analyzer.py
haoline/cli_typer.py
haoline/compare.py
haoline/compare_visualizations.py
haoline/edge_analysis.py
haoline/format_adapters.py
haoline/hardware.py
haoline/hierarchical_graph.py
haoline/html_export.py
haoline/layer_summary.py
haoline/llm_summarizer.py
haoline/op_icons.py
haoline/operational_profiling.py
haoline/patterns.py
haoline/pdf_generator.py
haoline/privacy.py
haoline/quantization_advisor.py
haoline/quantization_linter.py
haoline/report.py
haoline/report_sections.py
haoline/risks.py
haoline/schema.py
haoline/streamlit_app.py
haoline/streamlit_tabs.py
haoline/universal_ir.py
haoline/visualizations.py
haoline/visualize_yolo.py
haoline/web.py
haoline/.streamlit/config.toml
haoline/eval/__init__.py
haoline/eval/adapters.py
haoline/eval/cli.py
haoline/eval/comparison.py
haoline/eval/deployment.py
haoline/eval/schemas.py
haoline/examples/__init__.py
haoline/examples/basic_inspection.py
haoline/examples/compare_models.py
haoline/examples/hardware_estimation.py
haoline/formats/__init__.py
haoline/formats/coreml.py
haoline/formats/gguf.py
haoline/formats/openvino.py
haoline/formats/safetensors.py
haoline/formats/tensorrt.py
haoline/formats/tflite.py
haoline/formats/trt_comparison.py
haoline/tests/__init__.py
haoline/tests/conftest.py
haoline/tests/test_analyzer.py
haoline/tests/test_cli_typer.py
haoline/tests/test_compare_visualizations.py
haoline/tests/test_conversions.py
haoline/tests/test_edge_analysis.py
haoline/tests/test_eval.py
haoline/tests/test_format_adapters.py
haoline/tests/test_formats.py
haoline/tests/test_hardware.py
haoline/tests/test_hardware_recommender.py
haoline/tests/test_hierarchical_graph.py
haoline/tests/test_html_export.py
haoline/tests/test_layer_summary.py
haoline/tests/test_llm_patterns.py
haoline/tests/test_llm_summarizer.py
haoline/tests/test_patterns.py
haoline/tests/test_pytorch.py
haoline/tests/test_quantization_advisor.py
haoline/tests/test_report.py
haoline-1.3.0.dist-info/METADATA
haoline-1.3.0.dist-info/WHEEL
haoline-1.3.0.dist-info/entry_points.txt
haoline-1.3.0.dist-info/licenses/LICENSE
haoline-1.3.0.dist-info/RECORD
