Metadata-Version: 2.4
Name: haoline
Version: 1.3.0
Summary: HaoLine (皓线) - Universal Model Inspector. See what's really inside your models.
Project-URL: Homepage, https://github.com/mdayku/HaoLine
Project-URL: Documentation, https://github.com/mdayku/HaoLine#readme
Project-URL: Repository, https://github.com/mdayku/HaoLine
Project-URL: Issues, https://github.com/mdayku/HaoLine/issues
Project-URL: Changelog, https://github.com/mdayku/HaoLine/blob/main/CHANGELOG.md
Author-email: Marcus Day <marcusday3586@gmail.com>
License-Expression: MIT
License-File: LICENSE
Keywords: deep-learning,flops,machine-learning,memory,model-analysis,model-inspector,neural-network,onnx,parameters,profiling,pytorch,tensorflow,tensorrt
Classifier: Development Status :: 4 - Beta
Classifier: Environment :: Console
Classifier: Environment :: Web Environment
Classifier: Intended Audience :: Developers
Classifier: Intended Audience :: Science/Research
Classifier: License :: OSI Approved :: MIT License
Classifier: Operating System :: OS Independent
Classifier: Programming Language :: Python :: 3
Classifier: Programming Language :: Python :: 3.10
Classifier: Programming Language :: Python :: 3.11
Classifier: Programming Language :: Python :: 3.12
Classifier: Topic :: Scientific/Engineering :: Artificial Intelligence
Classifier: Topic :: Software Development :: Libraries :: Python Modules
Classifier: Typing :: Typed
Requires-Python: <3.13,>=3.10
Requires-Dist: matplotlib>=3.5.0
Requires-Dist: numpy>=1.20.0
Requires-Dist: onnx>=1.14.0
Requires-Dist: pydantic>=2.0.0
Requires-Dist: rich>=13.0.0
Requires-Dist: typer>=0.9.0
Provides-Extra: all
Requires-Dist: anthropic>=0.20.0; extra == 'all'
Requires-Dist: coremltools>=7.0; extra == 'all'
Requires-Dist: flax>=0.7.0; extra == 'all'
Requires-Dist: google-generativeai>=0.3.0; extra == 'all'
Requires-Dist: jax>=0.4.0; extra == 'all'
Requires-Dist: jaxlib>=0.4.0; extra == 'all'
Requires-Dist: matplotlib>=3.5.0; extra == 'all'
Requires-Dist: nvidia-ml-py>=12.0.0; extra == 'all'
Requires-Dist: onnxruntime>=1.16.0; extra == 'all'
Requires-Dist: openai>=1.0.0; extra == 'all'
Requires-Dist: openvino>=2024.0.0; extra == 'all'
Requires-Dist: playwright>=1.40.0; extra == 'all'
Requires-Dist: python-dotenv>=1.0.0; extra == 'all'
Requires-Dist: safetensors>=0.4.0; extra == 'all'
Requires-Dist: streamlit>=1.28.0; extra == 'all'
Requires-Dist: tensorflow>=2.14.0; extra == 'all'
Requires-Dist: tf2onnx>=1.16.0; extra == 'all'
Requires-Dist: ultralytics>=8.0.0; extra == 'all'
Provides-Extra: coreml
Requires-Dist: coremltools>=7.0; extra == 'coreml'
Provides-Extra: dev
Requires-Dist: black>=23.0.0; extra == 'dev'
Requires-Dist: mypy>=1.0.0; extra == 'dev'
Requires-Dist: pytest-cov>=4.0.0; extra == 'dev'
Requires-Dist: pytest>=7.0.0; extra == 'dev'
Requires-Dist: ruff>=0.1.0; extra == 'dev'
Provides-Extra: formats
Requires-Dist: safetensors>=0.4.0; extra == 'formats'
Provides-Extra: full
Requires-Dist: anthropic>=0.20.0; extra == 'full'
Requires-Dist: google-generativeai>=0.3.0; extra == 'full'
Requires-Dist: matplotlib>=3.5.0; extra == 'full'
Requires-Dist: nvidia-ml-py>=12.0.0; extra == 'full'
Requires-Dist: onnxruntime>=1.16.0; extra == 'full'
Requires-Dist: openai>=1.0.0; extra == 'full'
Requires-Dist: playwright>=1.40.0; extra == 'full'
Requires-Dist: python-dotenv>=1.0.0; extra == 'full'
Requires-Dist: safetensors>=0.4.0; extra == 'full'
Requires-Dist: streamlit>=1.28.0; extra == 'full'
Requires-Dist: tensorflow>=2.14.0; extra == 'full'
Requires-Dist: tf2onnx>=1.16.0; extra == 'full'
Requires-Dist: ultralytics>=8.0.0; extra == 'full'
Provides-Extra: gpu
Requires-Dist: nvidia-ml-py>=12.0.0; extra == 'gpu'
Provides-Extra: huggingface
Requires-Dist: huggingface-hub>=0.20.0; extra == 'huggingface'
Requires-Dist: optimum>=1.16.0; extra == 'huggingface'
Requires-Dist: transformers>=4.36.0; extra == 'huggingface'
Provides-Extra: jax
Requires-Dist: flax>=0.7.0; extra == 'jax'
Requires-Dist: jax>=0.4.0; extra == 'jax'
Requires-Dist: jaxlib>=0.4.0; extra == 'jax'
Provides-Extra: llm
Requires-Dist: anthropic>=0.20.0; extra == 'llm'
Requires-Dist: google-generativeai>=0.3.0; extra == 'llm'
Requires-Dist: openai>=1.0.0; extra == 'llm'
Requires-Dist: python-dotenv>=1.0.0; extra == 'llm'
Provides-Extra: openvino
Requires-Dist: openvino>=2024.0.0; extra == 'openvino'
Provides-Extra: pdf
Requires-Dist: playwright>=1.40.0; extra == 'pdf'
Provides-Extra: pytorch
Requires-Dist: torch>=2.0.0; extra == 'pytorch'
Provides-Extra: runtime
Requires-Dist: onnxruntime>=1.16.0; extra == 'runtime'
Provides-Extra: safetensors
Requires-Dist: safetensors>=0.4.0; extra == 'safetensors'
Provides-Extra: tensorflow
Requires-Dist: tensorflow>=2.14.0; extra == 'tensorflow'
Requires-Dist: tf2onnx>=1.16.0; extra == 'tensorflow'
Provides-Extra: tensorrt
Requires-Dist: tensorrt>=10.0.0; extra == 'tensorrt'
Provides-Extra: tflite
Requires-Dist: tflite-runtime>=2.14.0; (platform_system != 'Windows') and extra == 'tflite'
Requires-Dist: tflite2onnx>=0.4.0; extra == 'tflite'
Provides-Extra: ultralytics
Requires-Dist: ultralytics>=8.0.0; extra == 'ultralytics'
Provides-Extra: viz
Requires-Dist: matplotlib>=3.5.0; extra == 'viz'
Provides-Extra: web
Requires-Dist: streamlit>=1.28.0; extra == 'web'
